ncbitax2lin/__init__.py
ncbitax2lin/data_io.py
ncbitax2lin/fmt.py
ncbitax2lin/lineage.py
ncbitax2lin/ncbitax2lin.py
ncbitax2lin/struct.py
ncbitax2lin/utils.py
ncbitax2lin-3.0.0.dist-info/LICENSE.txt
ncbitax2lin-3.0.0.dist-info/METADATA
ncbitax2lin-3.0.0.dist-info/WHEEL
ncbitax2lin-3.0.0.dist-info/entry_points.txt
ncbitax2lin-3.0.0.dist-info/RECORD
