Metadata-Version: 2.1
Name: ncbitax2lin
Version: 3.0.0
Summary: A tool that converts NCBI taxonomy dump into lineages
Home-page: https://github.com/zyxue/ncbitax2lin
License: MIT
Author: Zhuyi Xue
Author-email: zhuyi.xue@alum.utoronto.ca
Requires-Python: >=3.9,<3.14
Classifier: License :: OSI Approved :: MIT License
Classifier: Programming Language :: Python :: 3
Classifier: Programming Language :: Python :: 3.9
Classifier: Programming Language :: Python :: 3.10
Classifier: Programming Language :: Python :: 3.11
Classifier: Programming Language :: Python :: 3.12
Classifier: Programming Language :: Python :: 3.13
Requires-Dist: fire (>=0.7.1,<0.8.0)
Requires-Dist: pandas (>=2.3.2,<3.0.0)
Requires-Dist: typing-extensions (>=4.15.0,<5.0.0)
